setup.py
mongoassist/__init__.py
mongoassist.egg-info/PKG-INFO
mongoassist.egg-info/SOURCES.txt
mongoassist.egg-info/dependency_links.txt
mongoassist.egg-info/requires.txt
mongoassist.egg-info/top_level.txt