Metadata-Version: 1.1
Name: mongoassist
Version: 1.2
Summary: A very simple mongodb client wrapper.
Home-page: https://github.com/guyingbo/mongoassist
Author: Gu Yingbo
Author-email: tensiongyb@gmail.com
License: MIT
Download-URL: https://github.com/guyingbo/mongoassist/archive/master.zip
Platform: any
Classifier: Development Status :: 5 - Production/Stable
Classifier: Intended Audience :: Developers
Classifier: License :: OSI Approved :: MIT License
Classifier: Operating System :: OS Independent
Classifier: Programming Language :: Python
Classifier: Topic :: Software Development :: Libraries :: Python Modules
